{"tetris":[{"name":"Chrystian","score":10},{"name":"Chrystian Tetris","score":999999999},{"name":"Kodologia.pl","score":20},{"name":"Korsan","score":19},{"name":"Chrystian","score":11},{"name":"Dvlr","score":666},{"name":"IE","score":8},{"name":"Husarz","score":9},{"name":"loser","score":1},{"name":"Diletta Leotta0","score":69},{"name":"Diletta Leotta1","score":69},{"name":"Diletta Leotta2","score":69},{"name":"Diletta Leotta3","score":69},{"name":"playerOne","score":"10","key":"0000"},{"name":"playerOne","score":"10","key":"0000"},{"name":"playerOne","score":"10","key":"0000"},{"name":"playerOne","score":"10","key":"0000"},{"name":"playerOne","score":"10","key":"0000"},{"name":"playerOne","score":"10","key":"0000"},{"name":"playerOne","score":"10","key":"0000"},{"name":"playerOne","score":"10","key":"0000"},{"name":"playerOne","score":"10","key":"0000"},{"name":"playerOne","score":"10","key":"0000"},{"name":"playerOne","score":"10","key":"0000"},{"name":"playerOne","score":"10","key":"0000"},{"name":"playerOne","score":"10","key":"0000"},{"name":"playerOne","score":"0","key":"0000"},{"name":"playerOne","score":"0","key":"0000"},{"name":"playerOne","score":"0","key":"0000"},{"name":"playerOne","score":"0","key":"0000"},{"name":"playerOne","score":"0","key":"0000"},{"name":"playerOne","score":"1","key":"0000"},{"name":"playerOne","score":"2","key":"0000"},{"name":"Mistrz","score":"1","key":"4587"},{"name":"Daniel","score":"1","key":"5555"}],"snake":[{"name":"Chrystian","score":10},{"name":"Chrystian Snake","score":999999999},{"name":"Kodologia.pl","score":20},{"name":"Korsan","score":19},{"name":"Chrystian","score":11},{"name":"Dvlr","score":666},{"name":"IE","score":8},{"name":"Husarz","score":9},{"name":"loser","score":1},{"name":"Diletta Leotta","score":69}]}